redis_sizer-1.0.0.dist-info/METADATA
redis_sizer-1.0.0.dist-info/WHEEL
redis_sizer-1.0.0.dist-info/entry_points.txt
redis_sizer-1.0.0.dist-info/licenses/LICENSE
redis_sizer/__init__.py
redis_sizer/cli.py
redis_sizer/models.py
redis_sizer/table_formatter.py
redis_sizer/tree_builder.py
redis_sizer-1.0.0.dist-info/RECORD
