Metadata-Version: 2.4
Name: redis-sizer
Version: 1.0.0
Summary: A simple command-line tool for analyzing memory usage across keys in a Redis database.
Author-Email: Mienxiu <mienxiu@gmail.com>
License-Expression: MIT
License-File: LICENSE
Project-URL: Homepage, https://github.com/mienxiu/redis-sizer
Project-URL: Documentation, https://github.com/mienxiu/redis-sizer
Project-URL: Repository, https://github.com/mienxiu/redis-sizer
Requires-Python: >=3.11
Requires-Dist: typer<0.16.0,>=0.15.2
Requires-Dist: redis<6.0.0,>=5.2.1
